README.md
setup.py
rofi_mopidy/__init__.py
rofi_mopidy/__main__.py
rofi_mopidy/options.py
rofi_mopidy/rofi_mopidy.py
rofi_mopidy/utils.py
rofi_mopidy.egg-info/PKG-INFO
rofi_mopidy.egg-info/SOURCES.txt
rofi_mopidy.egg-info/dependency_links.txt
rofi_mopidy.egg-info/entry_points.txt
rofi_mopidy.egg-info/requires.txt
rofi_mopidy.egg-info/top_level.txt
rofi_mopidy/auth/__init__.py
rofi_mopidy/auth/spotifyauth.py
rofi_mopidy/collectors/__init__.py
rofi_mopidy/collectors/local.py
rofi_mopidy/collectors/spotify.py